app/__init__.py
app/main.py
srv_rst_0ae_amp_test-1.0.0.dist-info/LICENSE
srv_rst_0ae_amp_test-1.0.0.dist-info/METADATA
srv_rst_0ae_amp_test-1.0.0.dist-info/WHEEL
srv_rst_0ae_amp_test-1.0.0.dist-info/top_level.txt
srv_rst_0ae_amp_test-1.0.0.dist-info/RECORD
