Metadata-Version: 2.1
Name: srv-rst-0ae-amp-test
Version: 1.0.0
Home-page: https://www.google.es
Author: Ángel Moreno
Author-email: a.morenoper@gmail.com
Classifier: Environment :: Console
Classifier: Intended Audience :: Developers
Classifier: License :: OSI Approved :: MIT License
Classifier: Operating System :: OS Independent
Classifier: Programming Language :: Python
Classifier: Programming Language :: Python :: 3.11
Classifier: Topic :: Utilities
License-File: LICENSE
Requires-Dist: numpy (>=1.25.1)
Requires-Dist: lib-cor-0ae-amp-json-utils (>=1.0.0)
